zernipax/__init__.py
zernipax/_version.py
zernipax/backend.py
zernipax/basis.py
zernipax/grid.py
zernipax/plotting.py
zernipax/zernike.py
zernipax-0.1.1.dist-info/METADATA
zernipax-0.1.1.dist-info/WHEEL
zernipax-0.1.1.dist-info/top_level.txt
zernipax-0.1.1.dist-info/RECORD
